<annotation>
	<folder>images</folder>
	<filename>7671.jpg</filename>
	<path>D:\Doan\Đồ án\data\images\7671.jpg</path>
	<source>
		<database>Unknown</database>
	</source>
	<size>
		<width>168</width>
		<height>224</height>
		<depth>3</depth>
	</size>
	<segmented>0</segmented>
	<object>
		<name>sock</name>
		<pose>Unspecified</pose>
		<truncated>0</truncated>
		<difficult>0</difficult>
		<bndbox>
			<xmin>18</xmin>
			<ymin>20</ymin>
			<xmax>80</xmax>
			<ymax>202</ymax>
		</bndbox>
	</object>
	<object>
		<name>sock</name>
		<pose>Unspecified</pose>
		<truncated>0</truncated>
		<difficult>0</difficult>
		<bndbox>
			<xmin>86</xmin>
			<ymin>25</ymin>
			<xmax>152</xmax>
			<ymax>205</ymax>
		</bndbox>
	</object>
</annotation>
