<annotation>
	<folder>images</folder>
	<filename>7683.jpg</filename>
	<path>D:\Doan\Đồ án\data\images\7683.jpg</path>
	<source>
		<database>Unknown</database>
	</source>
	<size>
		<width>168</width>
		<height>224</height>
		<depth>3</depth>
	</size>
	<segmented>0</segmented>
	<object>
		<name>clothoes</name>
		<pose>Unspecified</pose>
		<truncated>0</truncated>
		<difficult>0</difficult>
		<bndbox>
			<xmin>23</xmin>
			<ymin>52</ymin>
			<xmax>146</xmax>
			<ymax>199</ymax>
		</bndbox>
	</object>
</annotation>
